XigtifiedToolbox/FeatDict.py
XigtifiedToolbox/MorphTypeGuesser.py
XigtifiedToolbox/XigtReader.py
XigtifiedToolbox/__init__.py
XigtifiedToolbox/__main__.py
XigtifiedToolbox/collect_tags_toolbox.py
XigtifiedToolbox/collect_tags_xigt.py
XigtifiedToolbox/query_word_pos.py
XigtifiedToolbox/report_problems.py
XigtifiedToolbox/util.py
XigtifiedToolbox-0.0.4.dist-info/LICENSE
XigtifiedToolbox-0.0.4.dist-info/METADATA
XigtifiedToolbox-0.0.4.dist-info/WHEEL
XigtifiedToolbox-0.0.4.dist-info/top_level.txt
XigtifiedToolbox-0.0.4.dist-info/RECORD
