Metadata-Version: 2.1
Name: XigtifiedToolbox
Version: 0.0.4
Summary: Utilities for working with Xigt data
Home-page: https://git.ling.washington.edu/agg/xigtifiedtoolbox
Author: Elizabeth Conrad
Author-email: ecconrad@uw.edu
License: UNKNOWN
Project-URL: Bug Tracker, https://git.ling.washington.edu/agg/xigtifiedtoolbox
Platform: UNKNOWN
Classifier: Programming Language :: Python :: 3
Classifier: License :: OSI Approved :: MIT License
Classifier: Operating System :: OS Independent
Requires-Python: >=3.6
License-File: LICENSE
